mangodl/__init__.py
mangodl/__main__.py
mangodl/chapter.py
mangodl/cli.py
mangodl/filesys.py
mangodl/helpers.py
mangodl/login.py
mangodl/manga.py
mangodl/mangodl.py
mangodl/search.py
mangodl/config/__init__.py
mangodl/config/mangodl_config.py
mangodl/mangodl_logging/__init__.py
mangodl/mangodl_logging/mangodl_logging.ini
mangodl/mangodl_logging/mangodl_logging.py
mangodl-0.1.6.dist-info/LICENSE
mangodl-0.1.6.dist-info/METADATA
mangodl-0.1.6.dist-info/WHEEL
mangodl-0.1.6.dist-info/entry_points.txt
mangodl-0.1.6.dist-info/top_level.txt
mangodl-0.1.6.dist-info/RECORD
